LICENSE.txt
pyproject.toml
adskalman/__init__.py
adskalman/adskalman.py
adskalman/tests.py
adskalman/version.py
adskalman.egg-info/PKG-INFO
adskalman.egg-info/SOURCES.txt
adskalman.egg-info/dependency_links.txt
adskalman.egg-info/requires.txt
adskalman.egg-info/top_level.txt